hatch_plugin.py
metadata.json
pratik/__init__.py
pratik/color.py
pratik/functions.py
pratik/metadata.json
pratik/singleton.py
pratik/text.py
pratik/time.py
pratik-1.3.3.dist-info/METADATA
pratik-1.3.3.dist-info/WHEEL
pratik-1.3.3.dist-info/licenses/LICENSE
pratik-1.3.3.dist-info/RECORD
