Metadata-Version: 2.4
Name: Pratik
Version: 1.3.3
Summary: A library of various functions and classes helping to program more efficiently and more intuitively.
Project-URL: Homepage, https://github.com/LassaInora/Pratik
Project-URL: Repository, https://github.com/LassaInora/Pratik.git
Project-URL: Issues, https://github.com/LassaInora/Pratik/issues
Author-email: LassaInora <contact@lassainora.fr>
License-Expression: GPL-3.0-or-later
License-File: LICENSE
Keywords: Pratik,python,utils
Classifier: Development Status :: 5 - Production/Stable
Classifier: License :: OSI Approved :: GNU General Public License v3 (GPLv3)
Classifier: Operating System :: OS Independent
Classifier: Programming Language :: Python
Classifier: Programming Language :: Python :: 3
Classifier: Programming Language :: Python :: 3 :: Only
Classifier: Programming Language :: Python :: 3.7
Classifier: Programming Language :: Python :: 3.8
Classifier: Programming Language :: Python :: 3.9
Classifier: Programming Language :: Python :: 3.10
Classifier: Programming Language :: Python :: 3.11
Classifier: Programming Language :: Python :: 3.12
Classifier: Programming Language :: Python :: 3.13
Classifier: Topic :: Software Development :: Libraries
Requires-Python: >=3.7
